[ { "artist": { "url": "https://www.last.fm/music/Calvin+Harris", "name": "Calvin Harris", "image": [ { "size": "small", "#text": "https://lastfm.freetls.fastly.net/i/u/34s/2a96cbd8b46e442fc41c2b86b821562f.png" }, { "size": "medium", "#text": "https://lastfm.freetls.fastly.net/i/u/64s/2a96cbd8b46e442fc41c2b86b821562f.png" }, { "size": "large", "#text": "https://lastfm.freetls.fastly.net/i/u/174s/2a96cbd8b46e442fc41c2b86b821562f.png" }, { "size": "extralarge", "#text": "https://lastfm.freetls.fastly.net/i/u/300x300/2a96cbd8b46e442fc41c2b86b821562f.png" } ], "mbid": "" }, "mbid": "", "name": "Lovers In A Past Life (with Rag'n'Bone Man)", "image": [ { "size": "small", "#text": "https://lastfm.freetls.fastly.net/i/u/34s/039516e37cfd62b8f64c445daedb677f.png" }, { "size": "medium", "#text": "https://lastfm.freetls.fastly.net/i/u/64s/039516e37cfd62b8f64c445daedb677f.png" }, { "size": "large", "#text": "https://lastfm.freetls.fastly.net/i/u/174s/039516e37cfd62b8f64c445daedb677f.png" }, { "size": "extralarge", "#text": "https://lastfm.freetls.fastly.net/i/u/300x300/039516e37cfd62b8f64c445daedb677f.png" } ], "streamable": "0", "album": { "mbid": "", "#text": "Lovers In A Past Life (with Rag'n'Bone Man) [Cassö Remix]" }, "url": "https://www.last.fm/music/Calvin+Harris/_/Lovers+In+A+Past+Life+(with+Rag%27n%27Bone+Man)", "@attr": { "nowplaying": "true" }, "loved": "0" }, { "artist": { "url": "https://www.last.fm/music/Calvin+Harris", "name": "Calvin Harris", "image": [ { "size": "small", "#text": "https://lastfm.freetls.fastly.net/i/u/34s/2a96cbd8b46e442fc41c2b86b821562f.png" }, { "size": "medium", "#text": "https://lastfm.freetls.fastly.net/i/u/64s/2a96cbd8b46e442fc41c2b86b821562f.png" }, { "size": "large", "#text": "https://lastfm.freetls.fastly.net/i/u/174s/2a96cbd8b46e442fc41c2b86b821562f.png" }, { "size": "extralarge", "#text": "https://lastfm.freetls.fastly.net/i/u/300x300/2a96cbd8b46e442fc41c2b86b821562f.png" } ], "mbid": "" }, "date": { "uts": "1712737242", "#text": "10 Apr 2024, 08:20" }, "mbid": "", "name": "Lovers In A Past Life (with Rag'n'Bone Man) - Cassö Remix", "image": [ { "size": "small", "#text": "https://lastfm.freetls.fastly.net/i/u/34s/039516e37cfd62b8f64c445daedb677f.png" }, { "size": "medium", "#text": "https://lastfm.freetls.fastly.net/i/u/64s/039516e37cfd62b8f64c445daedb677f.png" }, { "size": "large", "#text": "https://lastfm.freetls.fastly.net/i/u/174s/039516e37cfd62b8f64c445daedb677f.png" }, { "size": "extralarge", "#text": "https://lastfm.freetls.fastly.net/i/u/300x300/039516e37cfd62b8f64c445daedb677f.png" } ], "url": "https://www.last.fm/music/Calvin+Harris/_/Lovers+In+A+Past+Life+(with+Rag%27n%27Bone+Man)+-+Cass%C3%B6+Remix", "streamable": "0", "album": { "mbid": "", "#text": "Lovers In A Past Life (with Rag'n'Bone Man) [Cassö Remix]" }, "loved": "0" }, { "artist": { "url": "https://www.last.fm/music/Calvin+Harris", "name": "Calvin Harris", "image": [ { "size": "small", "#text": "https://lastfm.freetls.fastly.net/i/u/34s/2a96cbd8b46e442fc41c2b86b821562f.png" }, { "size": "medium", "#text": "https://lastfm.freetls.fastly.net/i/u/64s/2a96cbd8b46e442fc41c2b86b821562f.png" }, { "size": "large", "#text": "https://lastfm.freetls.fastly.net/i/u/174s/2a96cbd8b46e442fc41c2b86b821562f.png" }, { "size": "extralarge", "#text": "https://lastfm.freetls.fastly.net/i/u/300x300/2a96cbd8b46e442fc41c2b86b821562f.png" } ], "mbid": "" }, "date": { "uts": "1712737086", "#text": "10 Apr 2024, 08:18" }, "mbid": "", "name": "Lovers In A Past Life (with Rag'n'Bone Man)", "image": [ { "size": "small", "#text": "https://lastfm.freetls.fastly.net/i/u/34s/039516e37cfd62b8f64c445daedb677f.png" }, { "size": "medium", "#text": "https://lastfm.freetls.fastly.net/i/u/64s/039516e37cfd62b8f64c445daedb677f.png" }, { "size": "large", "#text": "https://lastfm.freetls.fastly.net/i/u/174s/039516e37cfd62b8f64c445daedb677f.png" }, { "size": "extralarge", "#text": "https://lastfm.freetls.fastly.net/i/u/300x300/039516e37cfd62b8f64c445daedb677f.png" } ], "url": "https://www.last.fm/music/Calvin+Harris/_/Lovers+In+A+Past+Life+(with+Rag%27n%27Bone+Man)", "streamable": "0", "album": { "mbid": "", "#text": "Lovers In A Past Life (with Rag'n'Bone Man) [Cassö Remix]" }, "loved": "0" }, { "artist": { "url": "https://www.last.fm/music/Calvin+Harris", "name": "Calvin Harris", "image": [ { "size": "small", "#text": "https://lastfm.freetls.fastly.net/i/u/34s/2a96cbd8b46e442fc41c2b86b821562f.png" }, { "size": "medium", "#text": "https://lastfm.freetls.fastly.net/i/u/64s/2a96cbd8b46e442fc41c2b86b821562f.png" }, { "size": "large", "#text": "https://lastfm.freetls.fastly.net/i/u/174s/2a96cbd8b46e442fc41c2b86b821562f.png" }, { "size": "extralarge", "#text": "https://lastfm.freetls.fastly.net/i/u/300x300/2a96cbd8b46e442fc41c2b86b821562f.png" } ], "mbid": "" }, "date": { "uts": "1712736926", "#text": "10 Apr 2024, 08:15" }, "mbid": "", "name": "Lovers In A Past Life (with Rag'n'Bone Man) - Cassö Remix", "image": [ { "size": "small", "#text": "https://lastfm.freetls.fastly.net/i/u/34s/039516e37cfd62b8f64c445daedb677f.png" }, { "size": "medium", "#text": "https://lastfm.freetls.fastly.net/i/u/64s/039516e37cfd62b8f64c445daedb677f.png" }, { "size": "large", "#text": "https://lastfm.freetls.fastly.net/i/u/174s/039516e37cfd62b8f64c445daedb677f.png" }, { "size": "extralarge", "#text": "https://lastfm.freetls.fastly.net/i/u/300x300/039516e37cfd62b8f64c445daedb677f.png" } ], "url": "https://www.last.fm/music/Calvin+Harris/_/Lovers+In+A+Past+Life+(with+Rag%27n%27Bone+Man)+-+Cass%C3%B6+Remix", "streamable": "0", "album": { "mbid": "", "#text": "Lovers In A Past Life (with Rag'n'Bone Man) [Cassö Remix]" }, "loved": "0" }, { "artist": { "url": "https://www.last.fm/music/Calvin+Harris", "name": "Calvin Harris", "image": [ { "size": "small", "#text": "https://lastfm.freetls.fastly.net/i/u/34s/2a96cbd8b46e442fc41c2b86b821562f.png" }, { "size": "medium", "#text": "https://lastfm.freetls.fastly.net/i/u/64s/2a96cbd8b46e442fc41c2b86b821562f.png" }, { "size": "large", "#text": "https://lastfm.freetls.fastly.net/i/u/174s/2a96cbd8b46e442fc41c2b86b821562f.png" }, { "size": "extralarge", "#text": "https://lastfm.freetls.fastly.net/i/u/300x300/2a96cbd8b46e442fc41c2b86b821562f.png" } ], "mbid": "" }, "date": { "uts": "1712736770", "#text": "10 Apr 2024, 08:12" }, "mbid": "", "name": "Lovers In A Past Life (with Rag'n'Bone Man)", "image": [ { "size": "small", "#text": "https://lastfm.freetls.fastly.net/i/u/34s/039516e37cfd62b8f64c445daedb677f.png" }, { "size": "medium", "#text": "https://lastfm.freetls.fastly.net/i/u/64s/039516e37cfd62b8f64c445daedb677f.png" }, { "size": "large", "#text": "https://lastfm.freetls.fastly.net/i/u/174s/039516e37cfd62b8f64c445daedb677f.png" }, { "size": "extralarge", "#text": "https://lastfm.freetls.fastly.net/i/u/300x300/039516e37cfd62b8f64c445daedb677f.png" } ], "url": "https://www.last.fm/music/Calvin+Harris/_/Lovers+In+A+Past+Life+(with+Rag%27n%27Bone+Man)", "streamable": "0", "album": { "mbid": "", "#text": "Lovers In A Past Life (with Rag'n'Bone Man) [Cassö Remix]" }, "loved": "0" }, { "artist": { "url": "https://www.last.fm/music/Calvin+Harris", "name": "Calvin Harris", "image": [ { "size": "small", "#text": "https://lastfm.freetls.fastly.net/i/u/34s/2a96cbd8b46e442fc41c2b86b821562f.png" }, { "size": "medium", "#text": "https://lastfm.freetls.fastly.net/i/u/64s/2a96cbd8b46e442fc41c2b86b821562f.png" }, { "size": "large", "#text": "https://lastfm.freetls.fastly.net/i/u/174s/2a96cbd8b46e442fc41c2b86b821562f.png" }, { "size": "extralarge", "#text": "https://lastfm.freetls.fastly.net/i/u/300x300/2a96cbd8b46e442fc41c2b86b821562f.png" } ], "mbid": "" }, "date": { "uts": "1712736610", "#text": "10 Apr 2024, 08:10" }, "mbid": "", "name": "Lovers In A Past Life (with Rag'n'Bone Man) - Cassö Remix", "image": [ { "size": "small", "#text": "https://lastfm.freetls.fastly.net/i/u/34s/039516e37cfd62b8f64c445daedb677f.png" }, { "size": "medium", "#text": "https://lastfm.freetls.fastly.net/i/u/64s/039516e37cfd62b8f64c445daedb677f.png" }, { "size": "large", "#text": "https://lastfm.freetls.fastly.net/i/u/174s/039516e37cfd62b8f64c445daedb677f.png" }, { "size": "extralarge", "#text": "https://lastfm.freetls.fastly.net/i/u/300x300/039516e37cfd62b8f64c445daedb677f.png" } ], "url": "https://www.last.fm/music/Calvin+Harris/_/Lovers+In+A+Past+Life+(with+Rag%27n%27Bone+Man)+-+Cass%C3%B6+Remix", "streamable": "0", "album": { "mbid": "", "#text": "Lovers In A Past Life (with Rag'n'Bone Man) [Cassö Remix]" }, "loved": "0" }, { "artist": { "url": "https://www.last.fm/music/Calvin+Harris", "name": "Calvin Harris", "image": [ { "size": "small", "#text": "https://lastfm.freetls.fastly.net/i/u/34s/2a96cbd8b46e442fc41c2b86b821562f.png" }, { "size": "medium", "#text": "https://lastfm.freetls.fastly.net/i/u/64s/2a96cbd8b46e442fc41c2b86b821562f.png" }, { "size": "large", "#text": "https://lastfm.freetls.fastly.net/i/u/174s/2a96cbd8b46e442fc41c2b86b821562f.png" }, { "size": "extralarge", "#text": "https://lastfm.freetls.fastly.net/i/u/300x300/2a96cbd8b46e442fc41c2b86b821562f.png" } ], "mbid": "" }, "date": { "uts": "1712736454", "#text": "10 Apr 2024, 08:07" }, "mbid": "", "name": "Lovers In A Past Life (with Rag'n'Bone Man)", "image": [ { "size": "small", "#text": "https://lastfm.freetls.fastly.net/i/u/34s/039516e37cfd62b8f64c445daedb677f.png" }, { "size": "medium", "#text": "https://lastfm.freetls.fastly.net/i/u/64s/039516e37cfd62b8f64c445daedb677f.png" }, { "size": "large", "#text": "https://lastfm.freetls.fastly.net/i/u/174s/039516e37cfd62b8f64c445daedb677f.png" }, { "size": "extralarge", "#text": "https://lastfm.freetls.fastly.net/i/u/300x300/039516e37cfd62b8f64c445daedb677f.png" } ], "url": "https://www.last.fm/music/Calvin+Harris/_/Lovers+In+A+Past+Life+(with+Rag%27n%27Bone+Man)", "streamable": "0", "album": { "mbid": "", "#text": "Lovers In A Past Life (with Rag'n'Bone Man) [Cassö Remix]" }, "loved": "0" }, { "artist": { "url": "https://www.last.fm/music/Calvin+Harris", "name": "Calvin Harris", "image": [ { "size": "small", "#text": "https://lastfm.freetls.fastly.net/i/u/34s/2a96cbd8b46e442fc41c2b86b821562f.png" }, { "size": "medium", "#text": "https://lastfm.freetls.fastly.net/i/u/64s/2a96cbd8b46e442fc41c2b86b821562f.png" }, { "size": "large", "#text": "https://lastfm.freetls.fastly.net/i/u/174s/2a96cbd8b46e442fc41c2b86b821562f.png" }, { "size": "extralarge", "#text": "https://lastfm.freetls.fastly.net/i/u/300x300/2a96cbd8b46e442fc41c2b86b821562f.png" } ], "mbid": "" }, "date": { "uts": "1712736295", "#text": "10 Apr 2024, 08:04" }, "mbid": "", "name": "Lovers In A Past Life (with Rag'n'Bone Man) - Cassö Remix", "image": [ { "size": "small", "#text": "https://lastfm.freetls.fastly.net/i/u/34s/039516e37cfd62b8f64c445daedb677f.png" }, { "size": "medium", "#text": "https://lastfm.freetls.fastly.net/i/u/64s/039516e37cfd62b8f64c445daedb677f.png" }, { "size": "large", "#text": "https://lastfm.freetls.fastly.net/i/u/174s/039516e37cfd62b8f64c445daedb677f.png" }, { "size": "extralarge", "#text": "https://lastfm.freetls.fastly.net/i/u/300x300/039516e37cfd62b8f64c445daedb677f.png" } ], "url": "https://www.last.fm/music/Calvin+Harris/_/Lovers+In+A+Past+Life+(with+Rag%27n%27Bone+Man)+-+Cass%C3%B6+Remix", "streamable": "0", "album": { "mbid": "", "#text": "Lovers In A Past Life (with Rag'n'Bone Man) [Cassö Remix]" }, "loved": "0" }, { "artist": { "url": "https://www.last.fm/music/Calvin+Harris", "name": "Calvin Harris", "image": [ { "size": "small", "#text": "https://lastfm.freetls.fastly.net/i/u/34s/2a96cbd8b46e442fc41c2b86b821562f.png" }, { "size": "medium", "#text": "https://lastfm.freetls.fastly.net/i/u/64s/2a96cbd8b46e442fc41c2b86b821562f.png" }, { "size": "large", "#text": "https://lastfm.freetls.fastly.net/i/u/174s/2a96cbd8b46e442fc41c2b86b821562f.png" }, { "size": "extralarge", "#text": "https://lastfm.freetls.fastly.net/i/u/300x300/2a96cbd8b46e442fc41c2b86b821562f.png" } ], "mbid": "" }, "date": { "uts": "1712736139", "#text": "10 Apr 2024, 08:02" }, "mbid": "", "name": "Lovers In A Past Life (with Rag'n'Bone Man)", "image": [ { "size": "small", "#text": "https://lastfm.freetls.fastly.net/i/u/34s/039516e37cfd62b8f64c445daedb677f.png" }, { "size": "medium", "#text": "https://lastfm.freetls.fastly.net/i/u/64s/039516e37cfd62b8f64c445daedb677f.png" }, { "size": "large", "#text": "https://lastfm.freetls.fastly.net/i/u/174s/039516e37cfd62b8f64c445daedb677f.png" }, { "size": "extralarge", "#text": "https://lastfm.freetls.fastly.net/i/u/300x300/039516e37cfd62b8f64c445daedb677f.png" } ], "url": "https://www.last.fm/music/Calvin+Harris/_/Lovers+In+A+Past+Life+(with+Rag%27n%27Bone+Man)", "streamable": "0", "album": { "mbid": "", "#text": "Lovers In A Past Life (with Rag'n'Bone Man) [Cassö Remix]" }, "loved": "0" }, { "artist": { "url": "https://www.last.fm/music/Calvin+Harris", "name": "Calvin Harris", "image": [ { "size": "small", "#text": "https://lastfm.freetls.fastly.net/i/u/34s/2a96cbd8b46e442fc41c2b86b821562f.png" }, { "size": "medium", "#text": "https://lastfm.freetls.fastly.net/i/u/64s/2a96cbd8b46e442fc41c2b86b821562f.png" }, { "size": "large", "#text": "https://lastfm.freetls.fastly.net/i/u/174s/2a96cbd8b46e442fc41c2b86b821562f.png" }, { "size": "extralarge", "#text": "https://lastfm.freetls.fastly.net/i/u/300x300/2a96cbd8b46e442fc41c2b86b821562f.png" } ], "mbid": "" }, "date": { "uts": "1712735979", "#text": "10 Apr 2024, 07:59" }, "mbid": "", "name": "Lovers In A Past Life (with Rag'n'Bone Man) - Cassö Remix", "image": [ { "size": "small", "#text": "https://lastfm.freetls.fastly.net/i/u/34s/039516e37cfd62b8f64c445daedb677f.png" }, { "size": "medium", "#text": "https://lastfm.freetls.fastly.net/i/u/64s/039516e37cfd62b8f64c445daedb677f.png" }, { "size": "large", "#text": "https://lastfm.freetls.fastly.net/i/u/174s/039516e37cfd62b8f64c445daedb677f.png" }, { "size": "extralarge", "#text": "https://lastfm.freetls.fastly.net/i/u/300x300/039516e37cfd62b8f64c445daedb677f.png" } ], "url": "https://www.last.fm/music/Calvin+Harris/_/Lovers+In+A+Past+Life+(with+Rag%27n%27Bone+Man)+-+Cass%C3%B6+Remix", "streamable": "0", "album": { "mbid": "", "#text": "Lovers In A Past Life (with Rag'n'Bone Man) [Cassö Remix]" }, "loved": "0" }, { "artist": { "url": "https://www.last.fm/music/Calvin+Harris", "name": "Calvin Harris", "image": [ { "size": "small", "#text": "https://lastfm.freetls.fastly.net/i/u/34s/2a96cbd8b46e442fc41c2b86b821562f.png" }, { "size": "medium", "#text": "https://lastfm.freetls.fastly.net/i/u/64s/2a96cbd8b46e442fc41c2b86b821562f.png" }, { "size": "large", "#text": "https://lastfm.freetls.fastly.net/i/u/174s/2a96cbd8b46e442fc41c2b86b821562f.png" }, { "size": "extralarge", "#text": "https://lastfm.freetls.fastly.net/i/u/300x300/2a96cbd8b46e442fc41c2b86b821562f.png" } ], "mbid": "" }, "date": { "uts": "1712735823", "#text": "10 Apr 2024, 07:57" }, "mbid": "", "name": "Lovers In A Past Life (with Rag'n'Bone Man)", "image": [ { "size": "small", "#text": "https://lastfm.freetls.fastly.net/i/u/34s/039516e37cfd62b8f64c445daedb677f.png" }, { "size": "medium", "#text": "https://lastfm.freetls.fastly.net/i/u/64s/039516e37cfd62b8f64c445daedb677f.png" }, { "size": "large", "#text": "https://lastfm.freetls.fastly.net/i/u/174s/039516e37cfd62b8f64c445daedb677f.png" }, { "size": "extralarge", "#text": "https://lastfm.freetls.fastly.net/i/u/300x300/039516e37cfd62b8f64c445daedb677f.png" } ], "url": "https://www.last.fm/music/Calvin+Harris/_/Lovers+In+A+Past+Life+(with+Rag%27n%27Bone+Man)", "streamable": "0", "album": { "mbid": "", "#text": "Lovers In A Past Life (with Rag'n'Bone Man) [Cassö Remix]" }, "loved": "0" }, { "artist": { "url": "https://www.last.fm/music/Calvin+Harris", "name": "Calvin Harris", "image": [ { "size": "small", "#text": "https://lastfm.freetls.fastly.net/i/u/34s/2a96cbd8b46e442fc41c2b86b821562f.png" }, { "size": "medium", "#text": "https://lastfm.freetls.fastly.net/i/u/64s/2a96cbd8b46e442fc41c2b86b821562f.png" }, { "size": "large", "#text": "https://lastfm.freetls.fastly.net/i/u/174s/2a96cbd8b46e442fc41c2b86b821562f.png" }, { "size": "extralarge", "#text": "https://lastfm.freetls.fastly.net/i/u/300x300/2a96cbd8b46e442fc41c2b86b821562f.png" } ], "mbid": "" }, "date": { "uts": "1712735663", "#text": "10 Apr 2024, 07:54" }, "mbid": "", "name": "Lovers In A Past Life (with Rag'n'Bone Man) - Cassö Remix", "image": [ { "size": "small", "#text": "https://lastfm.freetls.fastly.net/i/u/34s/039516e37cfd62b8f64c445daedb677f.png" }, { "size": "medium", "#text": "https://lastfm.freetls.fastly.net/i/u/64s/039516e37cfd62b8f64c445daedb677f.png" }, { "size": "large", "#text": "https://lastfm.freetls.fastly.net/i/u/174s/039516e37cfd62b8f64c445daedb677f.png" }, { "size": "extralarge", "#text": "https://lastfm.freetls.fastly.net/i/u/300x300/039516e37cfd62b8f64c445daedb677f.png" } ], "url": "https://www.last.fm/music/Calvin+Harris/_/Lovers+In+A+Past+Life+(with+Rag%27n%27Bone+Man)+-+Cass%C3%B6+Remix", "streamable": "0", "album": { "mbid": "", "#text": "Lovers In A Past Life (with Rag'n'Bone Man) [Cassö Remix]" }, "loved": "0" }, { "artist": { "url": "https://www.last.fm/music/Calvin+Harris", "name": "Calvin Harris", "image": [ { "size": "small", "#text": "https://lastfm.freetls.fastly.net/i/u/34s/2a96cbd8b46e442fc41c2b86b821562f.png" }, { "size": "medium", "#text": "https://lastfm.freetls.fastly.net/i/u/64s/2a96cbd8b46e442fc41c2b86b821562f.png" }, { "size": "large", "#text": "https://lastfm.freetls.fastly.net/i/u/174s/2a96cbd8b46e442fc41c2b86b821562f.png" }, { "size": "extralarge", "#text": "https://lastfm.freetls.fastly.net/i/u/300x300/2a96cbd8b46e442fc41c2b86b821562f.png" } ], "mbid": "" }, "date": { "uts": "1712735507", "#text": "10 Apr 2024, 07:51" }, "mbid": "", "name": "Lovers In A Past Life (with Rag'n'Bone Man)", "image": [ { "size": "small", "#text": "https://lastfm.freetls.fastly.net/i/u/34s/039516e37cfd62b8f64c445daedb677f.png" }, { "size": "medium", "#text": "https://lastfm.freetls.fastly.net/i/u/64s/039516e37cfd62b8f64c445daedb677f.png" }, { "size": "large", "#text": "https://lastfm.freetls.fastly.net/i/u/174s/039516e37cfd62b8f64c445daedb677f.png" }, { "size": "extralarge", "#text": "https://lastfm.freetls.fastly.net/i/u/300x300/039516e37cfd62b8f64c445daedb677f.png" } ], "url": "https://www.last.fm/music/Calvin+Harris/_/Lovers+In+A+Past+Life+(with+Rag%27n%27Bone+Man)", "streamable": "0", "album": { "mbid": "", "#text": "Lovers In A Past Life (with Rag'n'Bone Man) [Cassö Remix]" }, "loved": "0" }, { "artist": { "url": "https://www.last.fm/music/Calvin+Harris", "name": "Calvin Harris", "image": [ { "size": "small", "#text": "https://lastfm.freetls.fastly.net/i/u/34s/2a96cbd8b46e442fc41c2b86b821562f.png" }, { "size": "medium", "#text": "https://lastfm.freetls.fastly.net/i/u/64s/2a96cbd8b46e442fc41c2b86b821562f.png" }, { "size": "large", "#text": "https://lastfm.freetls.fastly.net/i/u/174s/2a96cbd8b46e442fc41c2b86b821562f.png" }, { "size": "extralarge", "#text": "https://lastfm.freetls.fastly.net/i/u/300x300/2a96cbd8b46e442fc41c2b86b821562f.png" } ], "mbid": "" }, "date": { "uts": "1712735342", "#text": "10 Apr 2024, 07:49" }, "mbid": "", "name": "Lovers In A Past Life (with Rag'n'Bone Man) - Cassö Remix", "image": [ { "size": "small", "#text": "https://lastfm.freetls.fastly.net/i/u/34s/039516e37cfd62b8f64c445daedb677f.png" }, { "size": "medium", "#text": "https://lastfm.freetls.fastly.net/i/u/64s/039516e37cfd62b8f64c445daedb677f.png" }, { "size": "large", "#text": "https://lastfm.freetls.fastly.net/i/u/174s/039516e37cfd62b8f64c445daedb677f.png" }, { "size": "extralarge", "#text": "https://lastfm.freetls.fastly.net/i/u/300x300/039516e37cfd62b8f64c445daedb677f.png" } ], "url": "https://www.last.fm/music/Calvin+Harris/_/Lovers+In+A+Past+Life+(with+Rag%27n%27Bone+Man)+-+Cass%C3%B6+Remix", "streamable": "0", "album": { "mbid": "", "#text": "Lovers In A Past Life (with Rag'n'Bone Man) [Cassö Remix]" }, "loved": "0" }, { "artist": { "url": "https://www.last.fm/music/Gareth+Emery", "name": "Gareth Emery", "image": [ { "size": "small", "#text": "https://lastfm.freetls.fastly.net/i/u/34s/2a96cbd8b46e442fc41c2b86b821562f.png" }, { "size": "medium", "#text": "https://lastfm.freetls.fastly.net/i/u/64s/2a96cbd8b46e442fc41c2b86b821562f.png" }, { "size": "large", "#text": "https://lastfm.freetls.fastly.net/i/u/174s/2a96cbd8b46e442fc41c2b86b821562f.png" }, { "size": "extralarge", "#text": "https://lastfm.freetls.fastly.net/i/u/300x300/2a96cbd8b46e442fc41c2b86b821562f.png" } ], "mbid": "" }, "date": { "uts": "1712733552", "#text": "10 Apr 2024, 07:19" }, "mbid": "63955c18-553d-4efe-aca2-0490fbc5e86d", "name": "Drive: Refueled (Full Continuous Mix)", "image": [ { "size": "small", "#text": "https://lastfm.freetls.fastly.net/i/u/34s/2a96cbd8b46e442fc41c2b86b821562f.png" }, { "size": "medium", "#text": "https://lastfm.freetls.fastly.net/i/u/64s/2a96cbd8b46e442fc41c2b86b821562f.png" }, { "size": "large", "#text": "https://lastfm.freetls.fastly.net/i/u/174s/2a96cbd8b46e442fc41c2b86b821562f.png" }, { "size": "extralarge", "#text": "https://lastfm.freetls.fastly.net/i/u/300x300/2a96cbd8b46e442fc41c2b86b821562f.png" } ], "url": "https://www.last.fm/music/Gareth+Emery/_/Drive:+Refueled+(Full+Continuous+Mix)", "streamable": "0", "album": { "mbid": "", "#text": "Drive (Refueled)" }, "loved": "0" }, { "artist": { "url": "https://www.last.fm/music/Count+Counsellor", "name": "Count Counsellor", "image": [ { "size": "small", "#text": "https://lastfm.freetls.fastly.net/i/u/34s/2a96cbd8b46e442fc41c2b86b821562f.png" }, { "size": "medium", "#text": "https://lastfm.freetls.fastly.net/i/u/64s/2a96cbd8b46e442fc41c2b86b821562f.png" }, { "size": "large", "#text": "https://lastfm.freetls.fastly.net/i/u/174s/2a96cbd8b46e442fc41c2b86b821562f.png" }, { "size": "extralarge", "#text": "https://lastfm.freetls.fastly.net/i/u/300x300/2a96cbd8b46e442fc41c2b86b821562f.png" } ], "mbid": "" }, "date": { "uts": "1712733293", "#text": "10 Apr 2024, 07:14" }, "mbid": "", "name": "Open Eyes", "image": [ { "size": "small", "#text": "https://lastfm.freetls.fastly.net/i/u/34s/d74cd10c416df937e8e8e680ccdbc31a.jpg" }, { "size": "medium", "#text": "https://lastfm.freetls.fastly.net/i/u/64s/d74cd10c416df937e8e8e680ccdbc31a.jpg" }, { "size": "large", "#text": "https://lastfm.freetls.fastly.net/i/u/174s/d74cd10c416df937e8e8e680ccdbc31a.jpg" }, { "size": "extralarge", "#text": "https://lastfm.freetls.fastly.net/i/u/300x300/d74cd10c416df937e8e8e680ccdbc31a.jpg" } ], "url": "https://www.last.fm/music/Count+Counsellor/_/Open+Eyes", "streamable": "0", "album": { "mbid": "", "#text": "& The Friday Friends" }, "loved": "0" }, { "artist": { "url": "https://www.last.fm/music/Mike+Oldfield", "name": "Mike Oldfield", "image": [ { "size": "small", "#text": "https://lastfm.freetls.fastly.net/i/u/34s/2a96cbd8b46e442fc41c2b86b821562f.png" }, { "size": "medium", "#text": "https://lastfm.freetls.fastly.net/i/u/64s/2a96cbd8b46e442fc41c2b86b821562f.png" }, { "size": "large", "#text": "https://lastfm.freetls.fastly.net/i/u/174s/2a96cbd8b46e442fc41c2b86b821562f.png" }, { "size": "extralarge", "#text": "https://lastfm.freetls.fastly.net/i/u/300x300/2a96cbd8b46e442fc41c2b86b821562f.png" } ], "mbid": "" }, "date": { "uts": "1712733139", "#text": "10 Apr 2024, 07:12" }, "mbid": "13dce397-ebd0-3fea-8093-b8f3920adc03", "name": "Liberation", "image": [ { "size": "small", "#text": "https://lastfm.freetls.fastly.net/i/u/34s/7fbd777c26264ece806c72b766b35b8a.png" }, { "size": "medium", "#text": "https://lastfm.freetls.fastly.net/i/u/64s/7fbd777c26264ece806c72b766b35b8a.png" }, { "size": "large", "#text": "https://lastfm.freetls.fastly.net/i/u/174s/7fbd777c26264ece806c72b766b35b8a.png" }, { "size": "extralarge", "#text": "https://lastfm.freetls.fastly.net/i/u/300x300/7fbd777c26264ece806c72b766b35b8a.png" } ], "url": "https://www.last.fm/music/Mike+Oldfield/_/Liberation", "streamable": "0", "album": { "mbid": "87be17d7-c8ac-49ce-9ea2-a92fcca77530", "#text": "The Millennium Bell" }, "loved": "1" }, { "artist": { "url": "https://www.last.fm/music/Petit+Biscuit", "name": "Petit Biscuit", "image": [ { "size": "small", "#text": "https://lastfm.freetls.fastly.net/i/u/34s/2a96cbd8b46e442fc41c2b86b821562f.png" }, { "size": "medium", "#text": "https://lastfm.freetls.fastly.net/i/u/64s/2a96cbd8b46e442fc41c2b86b821562f.png" }, { "size": "large", "#text": "https://lastfm.freetls.fastly.net/i/u/174s/2a96cbd8b46e442fc41c2b86b821562f.png" }, { "size": "extralarge", "#text": "https://lastfm.freetls.fastly.net/i/u/300x300/2a96cbd8b46e442fc41c2b86b821562f.png" } ], "mbid": "" }, "date": { "uts": "1712732928", "#text": "10 Apr 2024, 07:08" }, "mbid": "0e8d2b09-9eba-4c9d-b60d-3e33c84ae8b3", "name": "Memories", "image": [ { "size": "small", "#text": "https://lastfm.freetls.fastly.net/i/u/34s/cf43b725bb412eac7eac53f5c5c9f25b.jpg" }, { "size": "medium", "#text": "https://lastfm.freetls.fastly.net/i/u/64s/cf43b725bb412eac7eac53f5c5c9f25b.jpg" }, { "size": "large", "#text": "https://lastfm.freetls.fastly.net/i/u/174s/cf43b725bb412eac7eac53f5c5c9f25b.jpg" }, { "size": "extralarge", "#text": "https://lastfm.freetls.fastly.net/i/u/300x300/cf43b725bb412eac7eac53f5c5c9f25b.jpg" } ], "url": "https://www.last.fm/music/Petit+Biscuit/_/Memories", "streamable": "0", "album": { "mbid": "c962dcbb-bbfd-4873-bda0-b7eac97b04ca", "#text": "Memories" }, "loved": "1" }, { "artist": { "url": "https://www.last.fm/music/Flo+Rida", "name": "Flo Rida", "image": [ { "size": "small", "#text": "https://lastfm.freetls.fastly.net/i/u/34s/2a96cbd8b46e442fc41c2b86b821562f.png" }, { "size": "medium", "#text": "https://lastfm.freetls.fastly.net/i/u/64s/2a96cbd8b46e442fc41c2b86b821562f.png" }, { "size": "large", "#text": "https://lastfm.freetls.fastly.net/i/u/174s/2a96cbd8b46e442fc41c2b86b821562f.png" }, { "size": "extralarge", "#text": "https://lastfm.freetls.fastly.net/i/u/300x300/2a96cbd8b46e442fc41c2b86b821562f.png" } ], "mbid": "" }, "date": { "uts": "1712732808", "#text": "10 Apr 2024, 07:06" }, "mbid": "20872fd5-6f1c-47f0-881d-78239a6b6a35", "name": "I Cry", "image": [ { "size": "small", "#text": "https://lastfm.freetls.fastly.net/i/u/34s/5a90a2ad14444c12bb236ebdba25a53e.png" }, { "size": "medium", "#text": "https://lastfm.freetls.fastly.net/i/u/64s/5a90a2ad14444c12bb236ebdba25a53e.png" }, { "size": "large", "#text": "https://lastfm.freetls.fastly.net/i/u/174s/5a90a2ad14444c12bb236ebdba25a53e.png" }, { "size": "extralarge", "#text": "https://lastfm.freetls.fastly.net/i/u/300x300/5a90a2ad14444c12bb236ebdba25a53e.png" } ], "url": "https://www.last.fm/music/Flo+Rida/_/I+Cry", "streamable": "0", "album": { "mbid": "0ace9b23-934d-4b58-a749-f0f33b883646", "#text": "Wild Ones" }, "loved": "0" } ]
